pdflinkchecker_cli/__init__.py
pdflinkchecker_cli/__version__.py
pdflinkchecker_cli/pdfchecker.py
pdflinkchecker_cli-0.2.0.dist-info/LICENSE
pdflinkchecker_cli-0.2.0.dist-info/METADATA
pdflinkchecker_cli-0.2.0.dist-info/WHEEL
pdflinkchecker_cli-0.2.0.dist-info/entry_points.txt
pdflinkchecker_cli-0.2.0.dist-info/top_level.txt
pdflinkchecker_cli-0.2.0.dist-info/RECORD
