Metadata-Version: 2.1
Name: pdflinkchecker-cli
Version: 0.2.0
Summary: Github Action and CLI tool to automatically check all links in a PDF for dead or broken links.
Home-page: https://github.com/a-nau/pdf-link-checker
Author: Alexander Naumann
Author-email: alex.code@mail.com
License: MIT
Classifier: License :: OSI Approved :: MIT License
Classifier: Programming Language :: Python
Classifier: Programming Language :: Python :: 3
Classifier: Programming Language :: Python :: 3.7
Classifier: Programming Language :: Python :: 3.8
Classifier: Programming Language :: Python :: 3.9
Classifier: Programming Language :: Python :: 3.10
Classifier: Programming Language :: Python :: Implementation :: PyPy
Requires-Python: >=3.7.0
License-File: LICENSE
Requires-Dist: PyPDF2 (==2.12.*)
Requires-Dist: tabulate
